{
    "Ar36": {
        "error": 0.00015724158469419578,
        "error_type": "",
        "fit": "previous",
        "references": [
            {
                "exclude": false,
                "record_id": "ba-03-F-45"
            }
        ],
        "value": 0.002237563185209268
    },
    "Ar37": {
        "error": 0.015686744552023,
        "error_type": "",
        "fit": "previous",
        "references": [
            {
                "exclude": false,
                "record_id": "ba-03-F-45"
            }
        ],
        "value": 0.01242475475900301
    },
    "Ar38": {
        "error": 0.004994712936052703,
        "error_type": "",
        "fit": "previous",
        "references": [
            {
                "exclude": false,
                "record_id": "ba-03-F-45"
            }
        ],
        "value": -0.0034720608773053663
    },
    "Ar39": {
        "error": 0.013574727883297742,
        "error_type": "",
        "fit": "previous",
        "references": [
            {
                "exclude": false,
                "record_id": "ba-03-F-45"
            }
        ],
        "value": 0.009009989307419622
    },
    "Ar40": {
        "error": 0.025084026008559447,
        "error_type": "",
        "fit": "previous",
        "references": [
            {
                "exclude": false,
                "record_id": "ba-03-F-45"
            }
        ],
        "value": 0.06325525431188384
    }
}