{
    "Ar36": {
        "error": 0.003911952831983408,
        "error_type": "SEM",
        "filter_outliers_dict": {
            "filter_outliers": true,
            "iterations": 2,
            "std_devs": 2
        },
        "fit": "Parabolic",
        "value": 2.1392183375606066
    },
    "Ar37": {
        "error": 0.013323291754095678,
        "error_type": "SEM",
        "filter_outliers_dict": {
            "filter_outliers": true,
            "iterations": 2,
            "std_devs": 2
        },
        "fit": "linear",
        "value": 0.09469843471682816
    },
    "Ar38": {
        "error": 0.004612773597282217,
        "error_type": "SEM",
        "filter_outliers_dict": {
            "filter_outliers": true,
            "iterations": 2,
            "std_devs": 2
        },
        "fit": "linear",
        "value": 0.5298125305839758
    },
    "Ar39": {
        "error": 0.013257693606505692,
        "error_type": "SEM",
        "filter_outliers_dict": {
            "filter_outliers": true,
            "iterations": 2,
            "std_devs": 2
        },
        "fit": "Parabolic",
        "value": 0.017270636396025087
    },
    "Ar40": {
        "error": 0.06095215105929429,
        "error_type": "SEM",
        "filter_outliers_dict": {
            "filter_outliers": true,
            "iterations": 2,
            "std_devs": 2
        },
        "fit": "Parabolic",
        "value": 654.8873697284921
    }
}